LICENSE
http_response/__init__.py
http_response/py.typed
http_response-0.0.8.dist-info/LICENSE
http_response-0.0.8.dist-info/METADATA
http_response-0.0.8.dist-info/WHEEL
http_response-0.0.8.dist-info/RECORD
