Metadata-Version: 2.1
Name: http_response
Version: 0.0.8
Summary: Python http response utils.
Home-page: https://github.com/ChenyangGao/python-modules/tree/main/http_response
License: MIT
Keywords: http,response
Author: ChenyangGao
Author-email: wosiwujm@gmail.com
Requires-Python: >=3.12,<4.0
Classifier: Development Status :: 5 - Production/Stable
Classifier: Intended Audience :: Developers
Classifier: License :: OSI Approved :: MIT License
Classifier: Operating System :: OS Independent
Classifier: Programming Language :: Python
Classifier: Programming Language :: Python :: 3
Classifier: Programming Language :: Python :: 3.12
Classifier: Programming Language :: Python :: 3.13
Classifier: Programming Language :: Python :: 3 :: Only
Classifier: Topic :: Software Development
Classifier: Topic :: Software Development :: Libraries
Classifier: Topic :: Software Development :: Libraries :: Python Modules
Requires-Dist: brotli
Requires-Dist: orjson
Requires-Dist: python-dicttools (>=0.0.2)
Requires-Dist: zstandard
Project-URL: Repository, https://github.com/ChenyangGao/python-modules/tree/main/http_response
